{
    "H": {
        "name": "氢",
        "category": "非金属",
        "atomicNumber": 1,
        "atomicMass": "1.00794",
        "electronConfig": "1s¹",
        "density": "0.0000899",
        "meltingPoint": "-259.14",
        "boilingPoint": "-252.87",
        "atomicRadius": "53",
        "electronegativity": "2.20",
        "ionizationEnergy": "13.598",
        "oxidationStates": "-1, +1",
        "crystalStructure": "六方晶系",
        "discovered": "1766"
    },
    "He": {
        "name": "氦",
        "category": "稀有气体",
        "atomicNumber": 2,
        "atomicMass": "4.002602",
        "electronConfig": "1s²",
        "density": "0.0001785",
        "meltingPoint": "-272.2",
        "boilingPoint": "-268.93",
        "atomicRadius": "31",
        "electronegativity": "0",
        "ionizationEnergy": "24.587",
        "oxidationStates": "0",
        "crystalStructure": "六方密堆积",
        "discovered": "1895"
    },
    "Li": {
        "name": "锂",
        "category": "碱金属",
        "atomicNumber": 3,
        "atomicMass": "6.941",
        "electronConfig": "[He]2s¹",
        "density": "0.534",
        "meltingPoint": "180.54",
        "boilingPoint": "1342",
        "atomicRadius": "167",
        "electronegativity": "0.98",
        "ionizationEnergy": "5.392",
        "oxidationStates": "+1",
        "crystalStructure": "体心立方",
        "discovered": "1817"
    },
    "Be": {
        "name": "铍",
        "category": "碱土金属",
        "atomicNumber": 4,
        "atomicMass": "9.012182",
        "electronConfig": "[He]2s²",
        "density": "1.85",
        "meltingPoint": "1287",
        "boilingPoint": "2470",
        "atomicRadius": "112",
        "electronegativity": "1.57",
        "ionizationEnergy": "9.323",
        "oxidationStates": "+2",
        "crystalStructure": "六方密堆积",
        "discovered": "1797"
    },
    "B": {
        "name": "硼",
        "category": "半金属",
        "atomicNumber": 5,
        "atomicMass": "10.811",
        "electronConfig": "[He]2s²2p¹",
        "density": "2.34",
        "meltingPoint": "2075",
        "boilingPoint": "4000",
        "atomicRadius": "87",
        "electronegativity": "2.04",
        "ionizationEnergy": "8.298",
        "oxidationStates": "+3",
        "crystalStructure": "菱形",
        "discovered": "1808"
    },
    "C": {
        "name": "碳",
        "category": "非金属",
        "atomicNumber": 6,
        "atomicMass": "12.0107",
        "electronConfig": "[He]2s²2p²",
        "density": "2.267",
        "meltingPoint": "3550",
        "boilingPoint": "4827",
        "atomicRadius": "67",
        "electronegativity": "2.55",
        "ionizationEnergy": "11.260",
        "oxidationStates": "-4, -3, -2, -1, +1, +2, +3, +4",
        "crystalStructure": "六方晶系/立方晶系",
        "discovered": "古代已知"
    },
    "N": {
        "name": "氮",
        "category": "非金属",
        "atomicNumber": 7,
        "atomicMass": "14.0067",
        "electronConfig": "[He]2s²2p³",
        "density": "0.001251",
        "meltingPoint": "-210.1",
        "boilingPoint": "-195.79",
        "atomicRadius": "56",
        "electronegativity": "3.04",
        "ionizationEnergy": "14.534",
        "oxidationStates": "-3, -2, -1, +1, +2, +3, +4, +5",
        "crystalStructure": "六方晶系",
        "discovered": "1772"
    },
    "O": {
        "name": "氧",
        "category": "非金属",
        "atomicNumber": 8,
        "atomicMass": "15.9994",
        "electronConfig": "[He]2s²2p⁴",
        "density": "0.001429",
        "meltingPoint": "-218.3",
        "boilingPoint": "-182.9",
        "atomicRadius": "48",
        "electronegativity": "3.44",
        "ionizationEnergy": "13.618",
        "oxidationStates": "-2, -1, +1, +2",
        "crystalStructure": "立方晶系",
        "discovered": "1774"
    },
    "F": {
        "name": "氟",
        "category": "卤素",
        "atomicNumber": 9,
        "atomicMass": "18.9984032",
        "electronConfig": "[He]2s²2p⁵",
        "density": "0.001696",
        "meltingPoint": "-219.6",
        "boilingPoint": "-188.12",
        "atomicRadius": "42",
        "electronegativity": "3.98",
        "ionizationEnergy": "17.423",
        "oxidationStates": "-1",
        "crystalStructure": "单斜晶系",
        "discovered": "1886"
    },
    "Ne": {
        "name": "氖",
        "category": "稀有气体",
        "atomicNumber": 10,
        "atomicMass": "20.1797",
        "electronConfig": "[He]2s²2p⁶",
        "density": "0.0008999",
        "meltingPoint": "-248.59",
        "boilingPoint": "-246.08",
        "atomicRadius": "38",
        "electronegativity": "0",
        "ionizationEnergy": "21.565",
        "oxidationStates": "0",
        "crystalStructure": "面心立方",
        "discovered": "1898"
    },
    "Na": {
        "name": "钠",
        "category": "碱金属",
        "atomicNumber": 11,
        "atomicMass": "22.98976928",
        "electronConfig": "[Ne]3s¹",
        "density": "0.971",
        "meltingPoint": "97.72",
        "boilingPoint": "883",
        "atomicRadius": "190",
        "electronegativity": "0.93",
        "ionizationEnergy": "5.139",
        "oxidationStates": "+1",
        "crystalStructure": "体心立方",
        "discovered": "1807"
    },
    "Mg": {
        "name": "镁",
        "category": "碱土金属",
        "atomicNumber": 12,
        "atomicMass": "24.3050",
        "electronConfig": "[Ne]3s²",
        "density": "1.738",
        "meltingPoint": "650",
        "boilingPoint": "1090",
        "atomicRadius": "145",
        "electronegativity": "1.31",
        "ionizationEnergy": "7.646",
        "oxidationStates": "+2",
        "crystalStructure": "六方密堆积",
        "discovered": "1755"
    },
    "Al": {
        "name": "铝",
        "category": "后过渡金属",
        "atomicNumber": 13,
        "atomicMass": "26.9815386",
        "electronConfig": "[Ne]3s²3p¹",
        "density": "2.698",
        "meltingPoint": "660.32",
        "boilingPoint": "2519",
        "atomicRadius": "118",
        "electronegativity": "1.61",
        "ionizationEnergy": "5.986",
        "oxidationStates": "+3",
        "crystalStructure": "面心立方",
        "discovered": "1825"
    },
    "Si": {
        "name": "硅",
        "category": "半金属",
        "atomicNumber": 14,
        "atomicMass": "28.0855",
        "electronConfig": "[Ne]3s²3p²",
        "density": "2.3296",
        "meltingPoint": "1414",
        "boilingPoint": "3265",
        "atomicRadius": "111",
        "electronegativity": "1.90",
        "ionizationEnergy": "8.152",
        "oxidationStates": "-4, +2, +4",
        "crystalStructure": "金刚石立方",
        "discovered": "1824"
    },
    "P": {
        "name": "磷",
        "category": "非金属",
        "atomicNumber": 15,
        "atomicMass": "30.973762",
        "electronConfig": "[Ne]3s²3p³",
        "density": "1.82",
        "meltingPoint": "44.2",
        "boilingPoint": "280.5",
        "atomicRadius": "98",
        "electronegativity": "2.19",
        "ionizationEnergy": "10.487",
        "oxidationStates": "-3, +3, +5",
        "crystalStructure": "正交晶系",
        "discovered": "1669"
    },
    "S": {
        "name": "硫",
        "category": "非金属",
        "atomicNumber": 16,
        "atomicMass": "32.065",
        "electronConfig": "[Ne]3s²3p⁴",
        "density": "2.067",
        "meltingPoint": "115.21",
        "boilingPoint": "444.72",
        "atomicRadius": "88",
        "electronegativity": "2.58",
        "ionizationEnergy": "10.360",
        "oxidationStates": "-2, +2, +4, +6",
        "crystalStructure": "正交晶系",
        "discovered": "古代已知"
    },
    "Cl": {
        "name": "氯",
        "category": "卤素",
        "atomicNumber": 17,
        "atomicMass": "35.453",
        "electronConfig": "[Ne]3s²3p⁵",
        "density": "0.003214",
        "meltingPoint": "-101.5",
        "boilingPoint": "-34.04",
        "atomicRadius": "79",
        "electronegativity": "3.16",
        "ionizationEnergy": "12.968",
        "oxidationStates": "-1, +1, +3, +5, +7",
        "crystalStructure": "正交晶系",
        "discovered": "1774"
    },
    "Ar": {
        "name": "氩",
        "category": "稀有气体",
        "atomicNumber": 18,
        "atomicMass": "39.948",
        "electronConfig": "[Ne]3s²3p⁶",
        "density": "0.0017837",
        "meltingPoint": "-189.3",
        "boilingPoint": "-185.8",
        "atomicRadius": "71",
        "electronegativity": "0",
        "ionizationEnergy": "15.760",
        "oxidationStates": "0",
        "crystalStructure": "面心立方",
        "discovered": "1894"
    },
    "K": {
        "name": "钾",
        "category": "碱金属",
        "atomicNumber": 19,
        "atomicMass": "39.0983",
        "electronConfig": "[Ar]4s¹",
        "density": "0.862",
        "meltingPoint": "63.38",
        "boilingPoint": "759",
        "atomicRadius": "243",
        "electronegativity": "0.82",
        "ionizationEnergy": "4.341",
        "oxidationStates": "+1",
        "crystalStructure": "体心立方",
        "discovered": "1807"
    },
    "Ca": {
        "name": "钙",
        "category": "碱土金属",
        "atomicNumber": 20,
        "atomicMass": "40.078",
        "electronConfig": "[Ar]4s²",
        "density": "1.54",
        "meltingPoint": "842",
        "boilingPoint": "1484",
        "atomicRadius": "194",
        "electronegativity": "1.00",
        "ionizationEnergy": "6.113",
        "oxidationStates": "+2",
        "crystalStructure": "面心立方",
        "discovered": "1808"
    },
    "Sc": {
        "name": "钪",
        "category": "过渡金属",
        "atomicNumber": 21,
        "atomicMass": "44.955912",
        "electronConfig": "[Ar]3d¹4s²",
        "density": "2.989",
        "meltingPoint": "1541",
        "boilingPoint": "2830",
        "atomicRadius": "184",
        "electronegativity": "1.36",
        "ionizationEnergy": "6.54",
        "oxidationStates": "+3",
        "crystalStructure": "六方密堆积",
        "discovered": "1879"
    },
    "Ti": {
        "name": "钛",
        "category": "过渡金属",
        "atomicNumber": 22,
        "atomicMass": "47.867",
        "electronConfig": "[Ar]3d²4s²",
        "density": "4.54",
        "meltingPoint": "1668",
        "boilingPoint": "3287",
        "atomicRadius": "176",
        "electronegativity": "1.54",
        "ionizationEnergy": "6.82",
        "oxidationStates": "-1, +2, +3, +4",
        "crystalStructure": "六方密堆积",
        "discovered": "1791"
    },
    "V": {
        "name": "钒",
        "category": "过渡金属",
        "atomicNumber": 23,
        "atomicMass": "50.9415",
        "electronConfig": "[Ar]3d³4s²",
        "density": "6.11",
        "meltingPoint": "1910",
        "boilingPoint": "3407",
        "atomicRadius": "171",
        "electronegativity": "1.63",
        "ionizationEnergy": "6.74",
        "oxidationStates": "-1, +2, +3, +4, +5",
        "crystalStructure": "体心立方",
        "discovered": "1801"
    },
    "Cr": {
        "name": "铬",
        "category": "过渡金属",
        "atomicNumber": 24,
        "atomicMass": "51.9961",
        "electronConfig": "[Ar]3d⁵4s¹",
        "density": "7.15",
        "meltingPoint": "1907",
        "boilingPoint": "2671",
        "atomicRadius": "166",
        "electronegativity": "1.66",
        "ionizationEnergy": "6.77",
        "oxidationStates": "-2, -1, +1, +2, +3, +4, +5, +6",
        "crystalStructure": "体心立方",
        "discovered": "1797"
    },
    "Mn": {
        "name": "锰",
        "category": "过渡金属",
        "atomicNumber": 25,
        "atomicMass": "54.938045",
        "electronConfig": "[Ar]3d⁵4s²",
        "density": "7.44",
        "meltingPoint": "1246",
        "boilingPoint": "2061",
        "atomicRadius": "161",
        "electronegativity": "1.55",
        "ionizationEnergy": "7.43",
        "oxidationStates": "-3, -2, -1, +1, +2, +3, +4, +5, +6, +7",
        "crystalStructure": "体心立方",
        "discovered": "1774"
    },
    "Fe": {
        "name": "铁",
        "category": "过渡金属",
        "atomicNumber": 26,
        "atomicMass": "55.845",
        "electronConfig": "[Ar]3d⁶4s²",
        "density": "7.874",
        "meltingPoint": "1538",
        "boilingPoint": "2862",
        "atomicRadius": "156",
        "electronegativity": "1.83",
        "ionizationEnergy": "7.90",
        "oxidationStates": "-2, -1, +1, +2, +3, +4, +5, +6",
        "crystalStructure": "体心立方",
        "discovered": "古代已知"
    },
    "Co": {
        "name": "钴",
        "category": "过渡金属",
        "atomicNumber": 27,
        "atomicMass": "58.933195",
        "electronConfig": "[Ar]3d⁷4s²",
        "density": "8.86",
        "meltingPoint": "1495",
        "boilingPoint": "2927",
        "atomicRadius": "152",
        "electronegativity": "1.88",
        "ionizationEnergy": "7.88",
        "oxidationStates": "-1, +1, +2, +3, +4, +5",
        "crystalStructure": "六方密堆积",
        "discovered": "1735"
    },
    "Ni": {
        "name": "镍",
        "category": "过渡金属",
        "atomicNumber": 28,
        "atomicMass": "58.6934",
        "electronConfig": "[Ar]3d⁸4s²",
        "density": "8.912",
        "meltingPoint": "1455",
        "boilingPoint": "2913",
        "atomicRadius": "149",
        "electronegativity": "1.91",
        "ionizationEnergy": "7.64",
        "oxidationStates": "-1, +1, +2, +3, +4",
        "crystalStructure": "面心立方",
        "discovered": "1751"
    },
    "Cu": {
        "name": "铜",
        "category": "过渡金属",
        "atomicNumber": 29,
        "atomicMass": "63.546",
        "electronConfig": "[Ar]3d¹⁰4s¹",
        "density": "8.96",
        "meltingPoint": "1084.62",
        "boilingPoint": "2562",
        "atomicRadius": "145",
        "electronegativity": "1.90",
        "ionizationEnergy": "7.73",
        "oxidationStates": "+1, +2, +3, +4",
        "crystalStructure": "面心立方",
        "discovered": "古代已知"
    },
    "Zn": {
        "name": "锌",
        "category": "过渡金属",
        "atomicNumber": 30,
        "atomicMass": "65.38",
        "electronConfig": "[Ar]3d¹⁰4s²",
        "density": "7.134",
        "meltingPoint": "419.53",
        "boilingPoint": "907",
        "atomicRadius": "142",
        "electronegativity": "1.65",
        "ionizationEnergy": "9.39",
        "oxidationStates": "+2",
        "crystalStructure": "六方密堆积",
        "discovered": "古代已知"
    },
    "Ga": {
        "name": "镓",
        "category": "后过渡金属",
        "atomicNumber": 31,
        "atomicMass": "69.723",
        "electronConfig": "[Ar]3d¹⁰4s²4p¹",
        "density": "5.907",
        "meltingPoint": "29.76",
        "boilingPoint": "2204",
        "atomicRadius": "136",
        "electronegativity": "1.81",
        "ionizationEnergy": "5.999",
        "oxidationStates": "+1, +2, +3",
        "crystalStructure": "正交晶系",
        "discovered": "1875"
    },
    "Ge": {
        "name": "锗",
        "category": "半金属",
        "atomicNumber": 32,
        "atomicMass": "72.64",
        "electronConfig": "[Ar]3d¹⁰4s²4p²",
        "density": "5.323",
        "meltingPoint": "938.25",
        "boilingPoint": "2820",
        "atomicRadius": "125",
        "electronegativity": "2.01",
        "ionizationEnergy": "7.90",
        "oxidationStates": "-4, +1, +2, +3, +4",
        "crystalStructure": "金刚石立方",
        "discovered": "1886"
    },
    "As": {
        "name": "砷",
        "category": "半金属",
        "atomicNumber": 33,
        "atomicMass": "74.92160",
        "electronConfig": "[Ar]3d¹⁰4s²4p³",
        "density": "5.776",
        "meltingPoint": "817",
        "boilingPoint": "614",
        "atomicRadius": "114",
        "electronegativity": "2.18",
        "ionizationEnergy": "9.81",
        "oxidationStates": "-3, +2, +3, +5",
        "crystalStructure": "三方晶系",
        "discovered": "古代已知"
    },
    "Se": {
        "name": "硒",
        "category": "非金属",
        "atomicNumber": 34,
        "atomicMass": "78.96",
        "electronConfig": "[Ar]3d¹⁰4s²4p⁴",
        "density": "4.809",
        "meltingPoint": "221",
        "boilingPoint": "685",
        "atomicRadius": "103",
        "electronegativity": "2.55",
        "ionizationEnergy": "9.75",
        "oxidationStates": "-2, +2, +4, +6",
        "crystalStructure": "六方晶系",
        "discovered": "1817"
    },
    "Br": {
        "name": "溴",
        "category": "卤素",
        "atomicNumber": 35,
        "atomicMass": "79.904",
        "electronConfig": "[Ar]3d¹⁰4s²4p⁵",
        "density": "3.122",
        "meltingPoint": "-7.2",
        "boilingPoint": "58.8",
        "atomicRadius": "94",
        "electronegativity": "2.96",
        "ionizationEnergy": "11.84",
        "oxidationStates": "-1, +1, +3, +4, +5, +7",
        "crystalStructure": "正交晶系",
        "discovered": "1826"
    },
    "Kr": {
        "name": "氪",
        "category": "稀有气体",
        "atomicNumber": 36,
        "atomicMass": "83.798",
        "electronConfig": "[Ar]3d¹⁰4s²4p⁶",
        "density": "0.003733",
        "meltingPoint": "-157.36",
        "boilingPoint": "-153.22",
        "atomicRadius": "88",
        "electronegativity": "3.00",
        "ionizationEnergy": "14.00",
        "oxidationStates": "0, +2",
        "crystalStructure": "面心立方",
        "discovered": "1898"
    },
    "Rb": {
        "name": "铷",
        "category": "碱金属",
        "atomicNumber": 37,
        "atomicMass": "85.4678",
        "electronConfig": "[Kr]5s¹",
        "density": "1.532",
        "meltingPoint": "39.31",
        "boilingPoint": "688",
        "atomicRadius": "265",
        "electronegativity": "0.82",
        "ionizationEnergy": "4.177",
        "oxidationStates": "+1",
        "crystalStructure": "体心立方",
        "discovered": "1861"
    },
    "Sr": {
        "name": "锶",
        "category": "碱土金属",
        "atomicNumber": 38,
        "atomicMass": "87.62",
        "electronConfig": "[Kr]5s²",
        "density": "2.64",
        "meltingPoint": "777",
        "boilingPoint": "1382",
        "atomicRadius": "219",
        "electronegativity": "0.95",
        "ionizationEnergy": "5.695",
        "oxidationStates": "+2",
        "crystalStructure": "面心立方",
        "discovered": "1790"
    },
    "Y": {
        "name": "钇",
        "category": "过渡金属",
        "atomicNumber": 39,
        "atomicMass": "88.90585",
        "electronConfig": "[Kr]4d¹5s²",
        "density": "4.469",
        "meltingPoint": "1526",
        "boilingPoint": "3345",
        "atomicRadius": "212",
        "electronegativity": "1.22",
        "ionizationEnergy": "6.217",
        "oxidationStates": "+3",
        "crystalStructure": "六方密堆积",
        "discovered": "1794"
    },
    "Zr": {
        "name": "锆",
        "category": "过渡金属",
        "atomicNumber": 40,
        "atomicMass": "91.224",
        "electronConfig": "[Kr]4d²5s²",
        "density": "6.506",
        "meltingPoint": "1855",
        "boilingPoint": "4409",
        "atomicRadius": "206",
        "electronegativity": "1.33",
        "ionizationEnergy": "6.634",
        "oxidationStates": "-2, +1, +2, +3, +4",
        "crystalStructure": "六方密堆积",
        "discovered": "1789"
    },
    "Nb": {
        "name": "铌",
        "category": "过渡金属",
        "atomicNumber": 41,
        "atomicMass": "92.90638",
        "electronConfig": "[Kr]4d⁴5s¹",
        "density": "8.57",
        "meltingPoint": "2477",
        "boilingPoint": "4744",
        "atomicRadius": "198",
        "electronegativity": "1.6",
        "ionizationEnergy": "6.759",
        "oxidationStates": "-1, +2, +3, +4, +5",
        "crystalStructure": "体心立方",
        "discovered": "1801"
    },
    "Mo": {
        "name": "钼",
        "category": "过渡金属",
        "atomicNumber": 42,
        "atomicMass": "95.96",
        "electronConfig": "[Kr]4d⁵5s¹",
        "density": "10.22",
        "meltingPoint": "2623",
        "boilingPoint": "4639",
        "atomicRadius": "190",
        "electronegativity": "2.16",
        "ionizationEnergy": "7.092",
        "oxidationStates": "-2, -1, +1, +2, +3, +4, +5, +6",
        "crystalStructure": "体心立方",
        "discovered": "1781"
    },
    "Tc": {
        "name": "锝",
        "category": "过渡金属",
        "atomicNumber": 43,
        "atomicMass": "98",
        "electronConfig": "[Kr]4d⁵5s²",
        "density": "11.5",
        "meltingPoint": "2157",
        "boilingPoint": "4265",
        "atomicRadius": "183",
        "electronegativity": "1.9",
        "ionizationEnergy": "7.28",
        "oxidationStates": "-3, -1, +1, +2, +3, +4, +5, +6, +7",
        "crystalStructure": "六方密堆积",
        "discovered": "1937"
    },
    "Ru": {
        "name": "钌",
        "category": "过渡金属",
        "atomicNumber": 44,
        "atomicMass": "101.07",
        "electronConfig": "[Kr]4d⁷5s¹",
        "density": "12.37",
        "meltingPoint": "2334",
        "boilingPoint": "4150",
        "atomicRadius": "178",
        "electronegativity": "2.2",
        "ionizationEnergy": "7.36",
        "oxidationStates": "-2, +1, +2, +3, +4, +5, +6, +7, +8",
        "crystalStructure": "六方密堆积",
        "discovered": "1844"
    },
    "Rh": {
        "name": "铑",
        "category": "过渡金属",
        "atomicNumber": 45,
        "atomicMass": "102.90550",
        "electronConfig": "[Kr]4d⁸5s¹",
        "density": "12.41",
        "meltingPoint": "1964",
        "boilingPoint": "3695",
        "atomicRadius": "173",
        "electronegativity": "2.28",
        "ionizationEnergy": "7.46",
        "oxidationStates": "-1, +1, +2, +3, +4, +5, +6",
        "crystalStructure": "面心立方",
        "discovered": "1803"
    },
    "Pd": {
        "name": "钯",
        "category": "过渡金属",
        "atomicNumber": 46,
        "atomicMass": "106.42",
        "electronConfig": "[Kr]4d¹⁰",
        "density": "12.02",
        "meltingPoint": "1554.9",
        "boilingPoint": "2963",
        "atomicRadius": "169",
        "electronegativity": "2.20",
        "ionizationEnergy": "8.34",
        "oxidationStates": "0, +1, +2, +3, +4",
        "crystalStructure": "面心立方",
        "discovered": "1803"
    },
    "Ag": {
        "name": "银",
        "category": "过渡金属",
        "atomicNumber": 47,
        "atomicMass": "107.8682",
        "electronConfig": "[Kr]4d¹⁰5s¹",
        "density": "10.49",
        "meltingPoint": "961.78",
        "boilingPoint": "2162",
        "atomicRadius": "165",
        "electronegativity": "1.93",
        "ionizationEnergy": "7.576",
        "oxidationStates": "+1, +2, +3",
        "crystalStructure": "面心立方",
        "discovered": "古代已知"
    },
    "Cd": {
        "name": "镉",
        "category": "过渡金属",
        "atomicNumber": 48,
        "atomicMass": "112.411",
        "electronConfig": "[Kr]4d¹⁰5s²",
        "density": "8.65",
        "meltingPoint": "321.07",
        "boilingPoint": "767",
        "atomicRadius": "161",
        "electronegativity": "1.69",
        "ionizationEnergy": "8.994",
        "oxidationStates": "+1, +2",
        "crystalStructure": "六方密堆积",
        "discovered": "1817"
    },
    "In": {
        "name": "铟",
        "category": "后过渡金属",
        "atomicNumber": 49,
        "atomicMass": "114.818",
        "electronConfig": "[Kr]4d¹⁰5s²5p¹",
        "density": "7.31",
        "meltingPoint": "156.6",
        "boilingPoint": "2072",
        "atomicRadius": "156",
        "electronegativity": "1.78",
        "ionizationEnergy": "5.786",
        "oxidationStates": "+1, +2, +3",
        "crystalStructure": "四方晶系",
        "discovered": "1863"
    },
    "Sn": {
        "name": "锡",
        "category": "后过渡金属",
        "atomicNumber": 50,
        "atomicMass": "118.710",
        "electronConfig": "[Kr]4d¹⁰5s²5p²",
        "density": "7.31",
        "meltingPoint": "231.93",
        "boilingPoint": "2602",
        "atomicRadius": "145",
        "electronegativity": "1.96",
        "ionizationEnergy": "7.344",
        "oxidationStates": "-4, +2, +4",
        "crystalStructure": "四方晶系",
        "discovered": "古代已知"
    },
    "Sb": {
        "name": "锑",
        "category": "半金属",
        "atomicNumber": 51,
        "atomicMass": "121.760",
        "electronConfig": "[Kr]4d¹⁰5s²5p³",
        "density": "6.697",
        "meltingPoint": "630.63",
        "boilingPoint": "1587",
        "atomicRadius": "133",
        "electronegativity": "2.05",
        "ionizationEnergy": "8.64",
        "oxidationStates": "-3, +3, +5",
        "crystalStructure": "三方晶系",
        "discovered": "古代已知"
    },
    "Te": {
        "name": "碲",
        "category": "半金属",
        "atomicNumber": 52,
        "atomicMass": "127.60",
        "electronConfig": "[Kr]4d¹⁰5s²5p⁴",
        "density": "6.24",
        "meltingPoint": "449.51",
        "boilingPoint": "988",
        "atomicRadius": "123",
        "electronegativity": "2.1",
        "ionizationEnergy": "9.01",
        "oxidationStates": "-2, +2, +4, +6",
        "crystalStructure": "三方晶系",
        "discovered": "1782"
    },
    "I": {
        "name": "碘",
        "category": "卤素",
        "atomicNumber": 53,
        "atomicMass": "126.90447",
        "electronConfig": "[Kr]4d¹⁰5s²5p⁵",
        "density": "4.94",
        "meltingPoint": "113.7",
        "boilingPoint": "184.3",
        "atomicRadius": "115",
        "electronegativity": "2.66",
        "ionizationEnergy": "10.451",
        "oxidationStates": "-1, +1, +3, +5, +7",
        "crystalStructure": "正交晶系",
        "discovered": "1811"
    },
    "Xe": {
        "name": "氙",
        "category": "稀有气体",
        "atomicNumber": 54,
        "atomicMass": "131.293",
        "electronConfig": "[Kr]4d¹⁰5s²5p⁶",
        "density": "0.005887",
        "meltingPoint": "-111.8",
        "boilingPoint": "-108.1",
        "atomicRadius": "108",
        "electronegativity": "2.6",
        "ionizationEnergy": "12.130",
        "oxidationStates": "0, +2, +4, +6, +8",
        "crystalStructure": "面心立方",
        "discovered": "1898"
    },
    "Cs": {
        "name": "铯",
        "category": "碱金属",
        "atomicNumber": 55,
        "atomicMass": "132.9054519",
        "electronConfig": "[Xe]6s¹",
        "density": "1.873",
        "meltingPoint": "28.44",
        "boilingPoint": "671",
        "atomicRadius": "298",
        "electronegativity": "0.79",
        "ionizationEnergy": "3.894",
        "oxidationStates": "+1",
        "crystalStructure": "体心立方",
        "discovered": "1860"
    },
    "Ba": {
        "name": "钡",
        "category": "碱土金属",
        "atomicNumber": 56,
        "atomicMass": "137.327",
        "electronConfig": "[Xe]6s²",
        "density": "3.594",
        "meltingPoint": "727",
        "boilingPoint": "1897",
        "atomicRadius": "253",
        "electronegativity": "0.89",
        "ionizationEnergy": "5.212",
        "oxidationStates": "+2",
        "crystalStructure": "体心立方",
        "discovered": "1774"
    },
    "La": {
        "name": "镧",
        "category": "镧系元素",
        "atomicNumber": 57,
        "atomicMass": "138.90547",
        "electronConfig": "[Xe]5d¹6s²",
        "density": "6.145",
        "meltingPoint": "920",
        "boilingPoint": "3464",
        "atomicRadius": "195",
        "electronegativity": "1.10",
        "ionizationEnergy": "5.577",
        "oxidationStates": "+3",
        "crystalStructure": "六方密堆积",
        "discovered": "1839"
    },
    "Ce": {
        "name": "铈",
        "category": "镧系元素",
        "atomicNumber": 58,
        "atomicMass": "140.116",
        "electronConfig": "[Xe]4f¹5d¹6s²",
        "density": "6.77",
        "meltingPoint": "795",
        "boilingPoint": "3443",
        "atomicRadius": "185",
        "electronegativity": "1.12",
        "ionizationEnergy": "5.539",
        "oxidationStates": "+2, +3, +4",
        "crystalStructure": "面心立方",
        "discovered": "1803"
    },
    "Pr": {
        "name": "镨",
        "category": "镧系元素",
        "atomicNumber": 59,
        "atomicMass": "140.90765",
        "electronConfig": "[Xe]4f³6s²",
        "density": "6.773",
        "meltingPoint": "935",
        "boilingPoint": "3520",
        "atomicRadius": "185",
        "electronegativity": "1.13",
        "ionizationEnergy": "5.473",
        "oxidationStates": "+2, +3, +4",
        "crystalStructure": "六方密堆积",
        "discovered": "1885"
    },
    "Nd": {
        "name": "钕",
        "category": "镧系元素",
        "atomicNumber": 60,
        "atomicMass": "144.242",
        "electronConfig": "[Xe]4f⁴6s²",
        "density": "7.007",
        "meltingPoint": "1024",
        "boilingPoint": "3074",
        "atomicRadius": "185",
        "electronegativity": "1.14",
        "ionizationEnergy": "5.525",
        "oxidationStates": "+2, +3, +4",
        "crystalStructure": "六方密堆积",
        "discovered": "1885"
    },
    "Pm": {
        "name": "钷",
        "category": "镧系元素",
        "atomicNumber": 61,
        "atomicMass": "145",
        "electronConfig": "[Xe]4f⁵6s²",
        "density": "7.26",
        "meltingPoint": "1042",
        "boilingPoint": "3000",
        "atomicRadius": "185",
        "electronegativity": "1.13",
        "ionizationEnergy": "5.582",
        "oxidationStates": "+3",
        "crystalStructure": "六方密堆积",
        "discovered": "1945"
    },
    "Sm": {
        "name": "钐",
        "category": "镧系元素",
        "atomicNumber": 62,
        "atomicMass": "150.36",
        "electronConfig": "[Xe]4f⁶6s²",
        "density": "7.52",
        "meltingPoint": "1074",
        "boilingPoint": "1794",
        "atomicRadius": "185",
        "electronegativity": "1.17",
        "ionizationEnergy": "5.644",
        "oxidationStates": "+2, +3",
        "crystalStructure": "三方晶系",
        "discovered": "1879"
    },
    "Eu": {
        "name": "铕",
        "category": "镧系元素",
        "atomicNumber": 63,
        "atomicMass": "151.964",
        "electronConfig": "[Xe]4f⁷6s²",
        "density": "5.243",
        "meltingPoint": "822",
        "boilingPoint": "1527",
        "atomicRadius": "185",
        "electronegativity": "1.2",
        "ionizationEnergy": "5.670",
        "oxidationStates": "+2, +3",
        "crystalStructure": "体心立方",
        "discovered": "1901"
    },
    "Gd": {
        "name": "钆",
        "category": "镧系元素",
        "atomicNumber": 64,
        "atomicMass": "157.25",
        "electronConfig": "[Xe]4f⁷5d¹6s²",
        "density": "7.895",
        "meltingPoint": "1313",
        "boilingPoint": "3273",
        "atomicRadius": "180",
        "electronegativity": "1.20",
        "ionizationEnergy": "6.150",
        "oxidationStates": "+3",
        "crystalStructure": "六方密堆积",
        "discovered": "1880"
    },
    "Tb": {
        "name": "铽",
        "category": "镧系元素",
        "atomicNumber": 65,
        "atomicMass": "158.92535",
        "electronConfig": "[Xe]4f⁹6s²",
        "density": "8.229",
        "meltingPoint": "1356",
        "boilingPoint": "3230",
        "atomicRadius": "177",
        "electronegativity": "1.1",
        "ionizationEnergy": "5.864",
        "oxidationStates": "+3, +4",
        "crystalStructure": "六方密堆积",
        "discovered": "1843"
    },
    "Dy": {
        "name": "镝",
        "category": "镧系元素",
        "atomicNumber": 66,
        "atomicMass": "162.500",
        "electronConfig": "[Xe]4f¹⁰6s²",
        "density": "8.55",
        "meltingPoint": "1412",
        "boilingPoint": "2567",
        "atomicRadius": "178",
        "electronegativity": "1.22",
        "ionizationEnergy": "5.939",
        "oxidationStates": "+3",
        "crystalStructure": "六方密堆积",
        "discovered": "1886"
    },
    "Ho": {
        "name": "钬",
        "category": "镧系元素",
        "atomicNumber": 67,
        "atomicMass": "164.93032",
        "electronConfig": "[Xe]4f¹¹6s²",
        "density": "8.795",
        "meltingPoint": "1474",
        "boilingPoint": "2700",
        "atomicRadius": "176",
        "electronegativity": "1.23",
        "ionizationEnergy": "6.022",
        "oxidationStates": "+3",
        "crystalStructure": "六方密堆积",
        "discovered": "1878"
    },
    "Er": {
        "name": "铒",
        "category": "镧系元素",
        "atomicNumber": 68,
        "atomicMass": "167.259",
        "electronConfig": "[Xe]4f¹²6s²",
        "density": "9.066",
        "meltingPoint": "1497",
        "boilingPoint": "2868",
        "atomicRadius": "176",
        "electronegativity": "1.24",
        "ionizationEnergy": "6.108",
        "oxidationStates": "+3",
        "crystalStructure": "六方密堆积",
        "discovered": "1842"
    },
    "Tm": {
        "name": "铥",
        "category": "镧系元素",
        "atomicNumber": 69,
        "atomicMass": "168.93421",
        "electronConfig": "[Xe]4f¹³6s²",
        "density": "9.321",
        "meltingPoint": "1545",
        "boilingPoint": "1950",
        "atomicRadius": "176",
        "electronegativity": "1.25",
        "ionizationEnergy": "6.184",
        "oxidationStates": "+2, +3",
        "crystalStructure": "六方密堆积",
        "discovered": "1879"
    },
    "Yb": {
        "name": "镱",
        "category": "镧系元素",
        "atomicNumber": 70,
        "atomicMass": "173.054",
        "electronConfig": "[Xe]4f¹⁴6s²",
        "density": "6.965",
        "meltingPoint": "819",
        "boilingPoint": "1196",
        "atomicRadius": "176",
        "electronegativity": "1.1",
        "ionizationEnergy": "6.254",
        "oxidationStates": "+2, +3",
        "crystalStructure": "面心立方",
        "discovered": "1878"
    },
    "Lu": {
        "name": "镥",
        "category": "镧系元素",
        "atomicNumber": 71,
        "atomicMass": "174.9668",
        "electronConfig": "[Xe]4f¹⁴5d¹6s²",
        "density": "9.84",
        "meltingPoint": "1663",
        "boilingPoint": "3402",
        "atomicRadius": "174",
        "electronegativity": "1.27",
        "ionizationEnergy": "5.426",
        "oxidationStates": "+3",
        "crystalStructure": "六方密堆积",
        "discovered": "1907"
    },
    "Hf": {
        "name": "铪",
        "category": "过渡金属",
        "atomicNumber": 72,
        "atomicMass": "178.49",
        "electronConfig": "[Xe]4f¹⁴5d²6s²",
        "density": "13.31",
        "meltingPoint": "2233",
        "boilingPoint": "4603",
        "atomicRadius": "159",
        "electronegativity": "1.3",
        "ionizationEnergy": "6.825",
        "oxidationStates": "+2, +3, +4",
        "crystalStructure": "六方密堆积",
        "discovered": "1923"
    },
    "Ta": {
        "name": "钽",
        "category": "过渡金属",
        "atomicNumber": 73,
        "atomicMass": "180.94788",
        "electronConfig": "[Xe]4f¹⁴5d³6s²",
        "density": "16.654",
        "meltingPoint": "3017",
        "boilingPoint": "5458",
        "atomicRadius": "146",
        "electronegativity": "1.5",
        "ionizationEnergy": "7.89",
        "oxidationStates": "-1, +2, +3, +4, +5",
        "crystalStructure": "体心立方",
        "discovered": "1802"
    },
    "W": {
        "name": "钨",
        "category": "过渡金属",
        "atomicNumber": 74,
        "atomicMass": "183.84",
        "electronConfig": "[Xe]4f¹⁴5d⁴6s²",
        "density": "19.25",
        "meltingPoint": "3422",
        "boilingPoint": "5555",
        "atomicRadius": "139",
        "electronegativity": "2.36",
        "ionizationEnergy": "7.98",
        "oxidationStates": "-2, -1, 0, +1, +2, +3, +4, +5, +6",
        "crystalStructure": "体心立方",
        "discovered": "1783"
    },
    "Re": {
        "name": "铼",
        "category": "过渡金属",
        "atomicNumber": 75,
        "atomicMass": "186.207",
        "electronConfig": "[Xe]4f¹⁴5d⁵6s²",
        "density": "21.02",
        "meltingPoint": "3186",
        "boilingPoint": "5596",
        "atomicRadius": "137",
        "electronegativity": "1.9",
        "ionizationEnergy": "7.88",
        "oxidationStates": "-3, -1, +1, +2, +3, +4, +5, +6, +7",
        "crystalStructure": "六方密堆积",
        "discovered": "1925"
    },
    "Os": {
        "name": "锇",
        "category": "过渡金属",
        "atomicNumber": 76,
        "atomicMass": "190.23",
        "electronConfig": "[Xe]4f¹⁴5d⁶6s²",
        "density": "22.61",
        "meltingPoint": "3033",
        "boilingPoint": "5012",
        "atomicRadius": "135",
        "electronegativity": "2.2",
        "ionizationEnergy": "8.7",
        "oxidationStates": "-2, -1, +1, +2, +3, +4, +5, +6, +7, +8",
        "crystalStructure": "六方密堆积",
        "discovered": "1803"
    },
    "Ir": {
        "name": "铱",
        "category": "过渡金属",
        "atomicNumber": 77,
        "atomicMass": "192.217",
        "electronConfig": "[Xe]4f¹⁴5d⁷6s²",
        "density": "22.56",
        "meltingPoint": "2466",
        "boilingPoint": "4428",
        "atomicRadius": "136",
        "electronegativity": "2.20",
        "ionizationEnergy": "9.1",
        "oxidationStates": "-3, -1, +1, +2, +3, +4, +5, +6",
        "crystalStructure": "面心立方",
        "discovered": "1803"
    },
    "Pt": {
        "name": "铂",
        "category": "过渡金属",
        "atomicNumber": 78,
        "atomicMass": "195.084",
        "electronConfig": "[Xe]4f¹⁴5d⁹6s¹",
        "density": "21.45",
        "meltingPoint": "1768.3",
        "boilingPoint": "3825",
        "atomicRadius": "139",
        "electronegativity": "2.28",
        "ionizationEnergy": "9.0",
        "oxidationStates": "-2, +1, +2, +3, +4, +5, +6",
        "crystalStructure": "面心立方",
        "discovered": "古代已知"
    },
    "Au": {
        "name": "金",
        "category": "过渡金属",
        "atomicNumber": 79,
        "atomicMass": "196.966569",
        "electronConfig": "[Xe]4f¹⁴5d¹⁰6s¹",
        "density": "19.32",
        "meltingPoint": "1064.18",
        "boilingPoint": "2856",
        "atomicRadius": "144",
        "electronegativity": "2.54",
        "ionizationEnergy": "9.226",
        "oxidationStates": "-1, +1, +2, +3, +5",
        "crystalStructure": "面心立方",
        "discovered": "古代已知"
    },
    "Hg": {
        "name": "汞",
        "category": "过渡金属",
        "atomicNumber": 80,
        "atomicMass": "200.59",
        "electronConfig": "[Xe]4f¹⁴5d¹⁰6s²",
        "density": "13.534",
        "meltingPoint": "-38.83",
        "boilingPoint": "356.73",
        "atomicRadius": "151",
        "electronegativity": "2.00",
        "ionizationEnergy": "10.438",
        "oxidationStates": "+1, +2",
        "crystalStructure": "三方晶系",
        "discovered": "古代已知"
    },
    "Tl": {
        "name": "铊",
        "category": "后过渡金属",
        "atomicNumber": 81,
        "atomicMass": "204.3833",
        "electronConfig": "[Xe]4f¹⁴5d¹⁰6s²6p¹",
        "density": "11.85",
        "meltingPoint": "304",
        "boilingPoint": "1473",
        "atomicRadius": "170",
        "electronegativity": "1.62",
        "ionizationEnergy": "6.108",
        "oxidationStates": "+1, +3",
        "crystalStructure": "六方密堆积",
        "discovered": "1861"
    },
    "Pb": {
        "name": "铅",
        "category": "后过渡金属",
        "atomicNumber": 82,
        "atomicMass": "207.2",
        "electronConfig": "[Xe]4f¹⁴5d¹⁰6s²6p²",
        "density": "11.34",
        "meltingPoint": "327.46",
        "boilingPoint": "1749",
        "atomicRadius": "175",
        "electronegativity": "1.87",
        "ionizationEnergy": "7.417",
        "oxidationStates": "-4, +2, +4",
        "crystalStructure": "面心立方",
        "discovered": "古代已知"
    },
    "Bi": {
        "name": "铋",
        "category": "后过渡金属",
        "atomicNumber": 83,
        "atomicMass": "208.98040",
        "electronConfig": "[Xe]4f¹⁴5d¹⁰6s²6p³",
        "density": "9.78",
        "meltingPoint": "271.3",
        "boilingPoint": "1564",
        "atomicRadius": "156",
        "electronegativity": "2.02",
        "ionizationEnergy": "7.289",
        "oxidationStates": "-3, +3, +5",
        "crystalStructure": "三方晶系",
        "discovered": "古代已知"
    },
    "Po": {
        "name": "钋",
        "category": "后过渡金属",
        "atomicNumber": 84,
        "atomicMass": "209",
        "electronConfig": "[Xe]4f¹⁴5d¹⁰6s²6p⁴",
        "density": "9.196",
        "meltingPoint": "254",
        "boilingPoint": "962",
        "atomicRadius": "168",
        "electronegativity": "2.0",
        "ionizationEnergy": "8.417",
        "oxidationStates": "-2, +2, +4, +6",
        "crystalStructure": "立方晶系",
        "discovered": "1898"
    },
    "At": {
        "name": "砹",
        "category": "卤素",
        "atomicNumber": 85,
        "atomicMass": "210",
        "electronConfig": "[Xe]4f¹⁴5d¹⁰6s²6p⁵",
        "density": "7",
        "meltingPoint": "302",
        "boilingPoint": "337",
        "atomicRadius": "150",
        "electronegativity": "2.2",
        "ionizationEnergy": "9.5",
        "oxidationStates": "-1, +1, +3, +5, +7",
        "crystalStructure": "面心立方",
        "discovered": "1940"
    },
    "Rn": {
        "name": "氡",
        "category": "稀有气体",
        "atomicNumber": 86,
        "atomicMass": "222",
        "electronConfig": "[Xe]4f¹⁴5d¹⁰6s²6p⁶",
        "density": "0.00973",
        "meltingPoint": "-71",
        "boilingPoint": "-61.7",
        "atomicRadius": "150",
        "electronegativity": "2.2",
        "ionizationEnergy": "10.745",
        "oxidationStates": "+2, +6",
        "crystalStructure": "面心立方",
        "discovered": "1900"
    },
    "Fr": {
        "name": "钫",
        "category": "碱金属",
        "atomicNumber": 87,
        "atomicMass": "223",
        "electronConfig": "[Rn]7s¹",
        "density": "1.87",
        "meltingPoint": "27",
        "boilingPoint": "677",
        "atomicRadius": "348",
        "electronegativity": "0.7",
        "ionizationEnergy": "4.0",
        "oxidationStates": "+1",
        "crystalStructure": "体心立方",
        "discovered": "1939"
    },
    "Ra": {
        "name": "镭",
        "category": "碱土金属",
        "atomicNumber": 88,
        "atomicMass": "226",
        "electronConfig": "[Rn]7s²",
        "density": "5.5",
        "meltingPoint": "700",
        "boilingPoint": "1737",
        "atomicRadius": "283",
        "electronegativity": "0.9",
        "ionizationEnergy": "5.279",
        "oxidationStates": "+2",
        "crystalStructure": "体心立方",
        "discovered": "1898"
    },
    "Ac": {
        "name": "锕",
        "category": "锕系元素",
        "atomicNumber": 89,
        "atomicMass": "227",
        "electronConfig": "[Rn]6d¹7s²",
        "density": "10.07",
        "meltingPoint": "1050",
        "boilingPoint": "3200",
        "atomicRadius": "215",
        "electronegativity": "1.1",
        "ionizationEnergy": "5.17",
        "oxidationStates": "+3",
        "crystalStructure": "面心立方",
        "discovered": "1899"
    },
    "Th": {
        "name": "钍",
        "category": "锕系元素",
        "atomicNumber": 90,
        "atomicMass": "232.03806",
        "electronConfig": "[Rn]6d²7s²",
        "density": "11.72",
        "meltingPoint": "1842",
        "boilingPoint": "4788",
        "atomicRadius": "206",
        "electronegativity": "1.3",
        "ionizationEnergy": "6.08",
        "oxidationStates": "+2, +3, +4",
        "crystalStructure": "面心立方",
        "discovered": "1828"
    },
    "Pa": {
        "name": "镤",
        "category": "锕系元素",
        "atomicNumber": 91,
        "atomicMass": "231.03588",
        "electronConfig": "[Rn]5f²6d¹7s²",
        "density": "15.37",
        "meltingPoint": "1841",
        "boilingPoint": "4300",
        "atomicRadius": "200",
        "electronegativity": "1.5",
        "ionizationEnergy": "5.89",
        "oxidationStates": "+3, +4, +5",
        "crystalStructure": "四方晶系",
        "discovered": "1913"
    },
    "U": {
        "name": "铀",
        "category": "锕系元素",
        "atomicNumber": 92,
        "atomicMass": "238.02891",
        "electronConfig": "[Rn]5f³6d¹7s²",
        "density": "19.1",
        "meltingPoint": "1135",
        "boilingPoint": "4131",
        "atomicRadius": "196",
        "electronegativity": "1.38",
        "ionizationEnergy": "6.194",
        "oxidationStates": "+3, +4, +5, +6",
        "crystalStructure": "正交晶系",
        "discovered": "1789"
    },
    "Np": {
        "name": "镎",
        "category": "锕系元素",
        "atomicNumber": 93,
        "atomicMass": "237",
        "electronConfig": "[Rn]5f⁴6d¹7s²",
        "density": "20.45",
        "meltingPoint": "644",
        "boilingPoint": "4000",
        "atomicRadius": "190",
        "electronegativity": "1.36",
        "ionizationEnergy": "6.266",
        "oxidationStates": "+3, +4, +5, +6, +7",
        "crystalStructure": "正交晶系",
        "discovered": "1940"
    },
    "Pu": {
        "name": "钚",
        "category": "锕系元素",
        "atomicNumber": 94,
        "atomicMass": "244",
        "electronConfig": "[Rn]5f⁶7s²",
        "density": "19.84",
        "meltingPoint": "640",
        "boilingPoint": "3230",
        "atomicRadius": "187",
        "electronegativity": "1.28",
        "ionizationEnergy": "6.026",
        "oxidationStates": "+3, +4, +5, +6, +7",
        "crystalStructure": "单斜晶系",
        "discovered": "1940"
    },
    "Am": {
        "name": "镅",
        "category": "锕系元素",
        "atomicNumber": 95,
        "atomicMass": "243",
        "electronConfig": "[Rn]5f⁷7s²",
        "density": "13.69",
        "meltingPoint": "1176",
        "boilingPoint": "2011",
        "atomicRadius": "180",
        "electronegativity": "1.3",
        "ionizationEnergy": "5.974",
        "oxidationStates": "+2, +3, +4, +5, +6",
        "crystalStructure": "六方密堆积",
        "discovered": "1944"
    },
    "Cm": {
        "name": "锔",
        "category": "锕系元素",
        "atomicNumber": 96,
        "atomicMass": "247",
        "electronConfig": "[Rn]5f⁷6d¹7s²",
        "density": "13.51",
        "meltingPoint": "1345",
        "boilingPoint": "3110",
        "atomicRadius": "169",
        "electronegativity": "1.3",
        "ionizationEnergy": "5.991",
        "oxidationStates": "+3, +4",
        "crystalStructure": "六方密堆积",
        "discovered": "1944"
    },
    "Bk": {
        "name": "锫",
        "category": "锕系元素",
        "atomicNumber": 97,
        "atomicMass": "247",
        "electronConfig": "[Rn]5f⁹7s²",
        "density": "14.78",
        "meltingPoint": "986",
        "boilingPoint": "2627",
        "atomicRadius": "170",
        "electronegativity": "1.3",
        "ionizationEnergy": "6.198",
        "oxidationStates": "+3, +4",
        "crystalStructure": "六方密堆积",
        "discovered": "1949"
    },
    "Cf": {
        "name": "锎",
        "category": "锕系元素",
        "atomicNumber": 98,
        "atomicMass": "251",
        "electronConfig": "[Rn]5f¹⁰7s²",
        "density": "15.1",
        "meltingPoint": "900",
        "boilingPoint": "1470",
        "atomicRadius": "170",
        "electronegativity": "1.3",
        "ionizationEnergy": "6.282",
        "oxidationStates": "+2, +3, +4",
        "crystalStructure": "六方密堆积",
        "discovered": "1950"
    },
    "Es": {
        "name": "锿",
        "category": "锕系元素",
        "atomicNumber": 99,
        "atomicMass": "252",
        "electronConfig": "[Rn]5f¹¹7s²",
        "density": "8.84",
        "meltingPoint": "860",
        "boilingPoint": "996",
        "atomicRadius": "200",
        "electronegativity": "1.3",
        "ionizationEnergy": "6.42",
        "oxidationStates": "+2, +3",
        "crystalStructure": "面心立方",
        "discovered": "1952"
    },
    "Fm": {
        "name": "镄",
        "category": "锕系元素",
        "atomicNumber": 100,
        "atomicMass": "257",
        "electronConfig": "[Rn]5f¹²7s²",
        "density": "unknown",
        "meltingPoint": "1527",
        "boilingPoint": "unknown",
        "atomicRadius": "200",
        "electronegativity": "1.3",
        "ionizationEnergy": "6.50",
        "oxidationStates": "+2, +3",
        "crystalStructure": "面心立方",
        "discovered": "1952"
    },
    "Md": {
        "name": "钔",
        "category": "锕系元素",
        "atomicNumber": 101,
        "atomicMass": "258",
        "electronConfig": "[Rn]5f¹³7s²",
        "density": "unknown",
        "meltingPoint": "827",
        "boilingPoint": "unknown",
        "atomicRadius": "200",
        "electronegativity": "1.3",
        "ionizationEnergy": "6.58",
        "oxidationStates": "+2, +3",
        "crystalStructure": "unknown",
        "discovered": "1955"
    },
    "No": {
        "name": "锘",
        "category": "锕系元素",
        "atomicNumber": 102,
        "atomicMass": "259",
        "electronConfig": "[Rn]5f¹⁴7s²",
        "density": "unknown",
        "meltingPoint": "827",
        "boilingPoint": "unknown",
        "atomicRadius": "200",
        "electronegativity": "1.3",
        "ionizationEnergy": "6.65",
        "oxidationStates": "+2, +3",
        "crystalStructure": "unknown",
        "discovered": "1958"
    },
    "Lr": {
        "name": "铹",
        "category": "锕系元素",
        "atomicNumber": 103,
        "atomicMass": "262",
        "electronConfig": "[Rn]5f¹⁴7s²7p¹",
        "density": "unknown",
        "meltingPoint": "1627",
        "boilingPoint": "unknown",
        "atomicRadius": "200",
        "electronegativity": "1.3",
        "ionizationEnergy": "4.9",
        "oxidationStates": "+3",
        "crystalStructure": "unknown",
        "discovered": "1961"
    },
    "Rf": {
        "name": "鑪",
        "category": "过渡金属",
        "atomicNumber": 104,
        "atomicMass": "267",
        "electronConfig": "[Rn]5f¹⁴6d²7s²",
        "density": "23",
        "meltingPoint": "2400",
        "boilingPoint": "5800",
        "atomicRadius": "unknown",
        "electronegativity": "unknown",
        "ionizationEnergy": "6.0",
        "oxidationStates": "+4",
        "crystalStructure": "unknown",
        "discovered": "1964"
    },
    "Db": {
        "name": "𨧀",
        "category": "过渡金属",
        "atomicNumber": 105,
        "atomicMass": "268",
        "electronConfig": "[Rn]5f¹⁴6d³7s²",
        "density": "29",
        "meltingPoint": "unknown",
        "boilingPoint": "unknown",
        "atomicRadius": "unknown",
        "electronegativity": "unknown",
        "ionizationEnergy": "unknown",
        "oxidationStates": "+5",
        "crystalStructure": "unknown",
        "discovered": "1967"
    },
    "Sg": {
        "name": "𨭎",
        "category": "过渡金属",
        "atomicNumber": 106,
        "atomicMass": "269",
        "electronConfig": "[Rn]5f¹⁴6d⁴7s²",
        "density": "35",
        "meltingPoint": "unknown",
        "boilingPoint": "unknown",
        "atomicRadius": "unknown",
        "electronegativity": "unknown",
        "ionizationEnergy": "unknown",
        "oxidationStates": "+6",
        "crystalStructure": "unknown",
        "discovered": "1974"
    },
    "Bh": {
        "name": "𨨏",
        "category": "过渡金属",
        "atomicNumber": 107,
        "atomicMass": "270",
        "electronConfig": "[Rn]5f¹⁴6d⁵7s²",
        "density": "37",
        "meltingPoint": "unknown",
        "boilingPoint": "unknown",
        "atomicRadius": "unknown",
        "electronegativity": "unknown",
        "ionizationEnergy": "unknown",
        "oxidationStates": "+7",
        "crystalStructure": "unknown",
        "discovered": "1981"
    },
    "Hs": {
        "name": "𨭆",
        "category": "过渡金属",
        "atomicNumber": 108,
        "atomicMass": "269",
        "electronConfig": "[Rn]5f¹⁴6d⁶7s²",
        "density": "41",
        "meltingPoint": "unknown",
        "boilingPoint": "unknown",
        "atomicRadius": "unknown",
        "electronegativity": "unknown",
        "ionizationEnergy": "unknown",
        "oxidationStates": "+8",
        "crystalStructure": "unknown",
        "discovered": "1984"
    },
    "Mt": {
        "name": "鿏",
        "category": "过渡金属",
        "atomicNumber": 109,
        "atomicMass": "278",
        "electronConfig": "[Rn]5f¹⁴6d⁷7s²",
        "density": "35",
        "meltingPoint": "unknown",
        "boilingPoint": "unknown",
        "atomicRadius": "unknown",
        "electronegativity": "unknown",
        "ionizationEnergy": "unknown",
        "oxidationStates": "+3, +4, +6",
        "crystalStructure": "unknown",
        "discovered": "1982"
    },
    "Ds": {
        "name": "𫟼",
        "category": "过渡金属",
        "atomicNumber": 110,
        "atomicMass": "281",
        "electronConfig": "[Rn]5f¹⁴6d⁹7s¹",
        "density": "unknown",
        "meltingPoint": "unknown",
        "boilingPoint": "unknown",
        "atomicRadius": "unknown",
        "electronegativity": "unknown",
        "ionizationEnergy": "unknown",
        "oxidationStates": "+6",
        "crystalStructure": "unknown",
        "discovered": "1994"
    },
    "Rg": {
        "name": "𬬭",
        "category": "过渡金属",
        "atomicNumber": 111,
        "atomicMass": "282",
        "electronConfig": "[Rn]5f¹⁴6d¹⁰7s¹",
        "density": "unknown",
        "meltingPoint": "unknown",
        "boilingPoint": "unknown",
        "atomicRadius": "unknown",
        "electronegativity": "unknown",
        "ionizationEnergy": "unknown",
        "oxidationStates": "+1, +3",
        "crystalStructure": "unknown",
        "discovered": "1994"
    },
    "Cn": {
        "name": "鿔",
        "category": "过渡金属",
        "atomicNumber": 112,
        "atomicMass": "285",
        "electronConfig": "[Rn]5f¹⁴6d¹⁰7s²",
        "density": "unknown",
        "meltingPoint": "unknown",
        "boilingPoint": "unknown",
        "atomicRadius": "unknown",
        "electronegativity": "unknown",
        "ionizationEnergy": "unknown",
        "oxidationStates": "+2, +4",
        "crystalStructure": "unknown",
        "discovered": "1996"
    },
    "Nh": {
        "name": "鉨",
        "category": "后过渡金属",
        "atomicNumber": 113,
        "atomicMass": "286",
        "electronConfig": "[Rn]5f¹⁴6d¹⁰7s²7p¹",
        "density": "unknown",
        "meltingPoint": "unknown",
        "boilingPoint": "unknown",
        "atomicRadius": "unknown",
        "electronegativity": "unknown",
        "ionizationEnergy": "unknown",
        "oxidationStates": "+1, +3, +5",
        "crystalStructure": "unknown",
        "discovered": "2003"
    },
    "Fl": {
        "name": "𫓧",
        "category": "后过渡金属",
        "atomicNumber": 114,
        "atomicMass": "289",
        "electronConfig": "[Rn]5f¹⁴6d¹⁰7s²7p²",
        "density": "unknown",
        "meltingPoint": "unknown",
        "boilingPoint": "unknown",
        "atomicRadius": "unknown",
        "electronegativity": "unknown",
        "ionizationEnergy": "unknown",
        "oxidationStates": "+2, +4",
        "crystalStructure": "unknown",
        "discovered": "1998"
    },
    "Mc": {
        "name": "镆",
        "category": "后过渡金属",
        "atomicNumber": 115,
        "atomicMass": "290",
        "electronConfig": "[Rn]5f¹⁴6d¹⁰7s²7p³",
        "density": "unknown",
        "meltingPoint": "unknown",
        "boilingPoint": "unknown",
        "atomicRadius": "unknown",
        "electronegativity": "unknown",
        "ionizationEnergy": "unknown",
        "oxidationStates": "+1, +3",
        "crystalStructure": "unknown",
        "discovered": "2003"
    },
    "Lv": {
        "name": "鉝",
        "category": "后过渡金属",
        "atomicNumber": 116,
        "atomicMass": "293",
        "electronConfig": "[Rn]5f¹⁴6d¹⁰7s²7p⁴",
        "density": "unknown",
        "meltingPoint": "unknown",
        "boilingPoint": "unknown",
        "atomicRadius": "unknown",
        "electronegativity": "unknown",
        "ionizationEnergy": "unknown",
        "oxidationStates": "+2, +4",
        "crystalStructure": "unknown",
        "discovered": "2000"
    },
    "Ts": {
        "name": "鿬",
        "category": "卤素",
        "atomicNumber": 117,
        "atomicMass": "294",
        "electronConfig": "[Rn]5f¹⁴6d¹⁰7s²7p⁵",
        "density": "unknown",
        "meltingPoint": "unknown",
        "boilingPoint": "unknown",
        "atomicRadius": "unknown",
        "electronegativity": "unknown",
        "ionizationEnergy": "unknown",
        "oxidationStates": "-1, +1, +3, +5",
        "crystalStructure": "unknown",
        "discovered": "2010"
    },
    "Og": {
        "name": "鿫",
        "category": "稀有气体",
        "atomicNumber": 118,
        "atomicMass": "294",
        "electronConfig": "[Rn]5f¹⁴6d¹⁰7s²7p⁶",
        "density": "unknown",
        "meltingPoint": "unknown",
        "boilingPoint": "unknown",
        "atomicRadius": "unknown",
        "electronegativity": "unknown",
        "ionizationEnergy": "unknown",
        "oxidationStates": "0, +2, +4",
        "crystalStructure": "unknown",
        "discovered": "2002"
    }
} 