{
  "atoms": [
    {
      "element": "C",
      "position": [
        6.739481816632663,
        0.07263522212704633,
        0.5530349907123224
      ],
      "atomic_number": 6
    },
    {
      "element": "C",
      "position": [
        5.261928176824399,
        0.0700632240669804,
        0.29210450888313605
      ],
      "atomic_number": 6
    },
    {
      "element": "C",
      "position": [
        4.659885254808872,
        -1.0124035492714927,
        -0.35765416109271336
      ],
      "atomic_number": 6
    },
    {
      "element": "C",
      "position": [
        3.289264128051706,
        -1.0007277295336294,
        -0.6288768425203012
      ],
      "atomic_number": 6
    },
    {
      "element": "C",
      "position": [
        2.500854387089243,
        0.09725265293512476,
        -0.2614898867032792
      ],
      "atomic_number": 6
    },
    {
      "element": "C",
      "position": [
        1.0392554009650832,
        0.059976364404700784,
        -0.5737844960505001
      ],
      "atomic_number": 6
    },
    {
      "element": "O",
      "position": [
        0.5982661575900774,
        -0.8505759113979325,
        -1.2723015094564656
      ],
      "atomic_number": 8
    },
    {
      "element": "C",
      "position": [
        0.14926482561079357,
        1.164757917522955,
        -0.025196148578156104
      ],
      "atomic_number": 6
    },
    {
      "element": "C",
      "position": [
        -1.345203973881191,
        0.8952984046164043,
        -0.2327806437008913
      ],
      "atomic_number": 6
    },
    {
      "element": "C",
      "position": [
        -1.8697013842620143,
        -0.19211379729609618,
        0.7197855782154972
      ],
      "atomic_number": 6
    },
    {
      "element": "N",
      "position": [
        -3.274718334524869,
        -0.5701629948186524,
        0.5902371315360079
      ],
      "atomic_number": 7
    },
    {
      "element": "C",
      "position": [
        -4.243917811105146,
        0.5122076017607118,
        0.6975204235836303
      ],
      "atomic_number": 6
    },
    {
      "element": "C",
      "position": [
        -5.542183924368026,
        -0.18713678512614057,
        0.3247591831658448
      ],
      "atomic_number": 6
    },
    {
      "element": "C",
      "position": [
        -5.127946652728028,
        -1.3067493534357206,
        -0.6264074197297874
      ],
      "atomic_number": 6
    },
    {
      "element": "C",
      "position": [
        -3.604095121677766,
        -1.2810607860693808,
        -0.6417168064564978
      ],
      "atomic_number": 6
    },
    {
      "element": "C",
      "position": [
        3.1047257815308753,
        1.1893987740501388,
        0.37147968467304704
      ],
      "atomic_number": 6
    },
    {
      "element": "C",
      "position": [
        4.477467304044407,
        1.1752408494288038,
        0.6417274858299565
      ],
      "atomic_number": 6
    },
    {
      "element": "H",
      "position": [
        7.269241034152059,
        0.506919260376441,
        -0.3003459082131136
      ],
      "atomic_number": 1
    },
    {
      "element": "H",
      "position": [
        6.976411140235884,
        0.6538636133945116,
        1.450389445539319
      ],
      "atomic_number": 1
    },
    {
      "element": "H",
      "position": [
        7.108593734432604,
        -0.9449540506630085,
        0.7188345379588146
      ],
      "atomic_number": 1
    },
    {
      "element": "H",
      "position": [
        5.252315190091102,
        -1.8742170255133006,
        -0.6581172953838902
      ],
      "atomic_number": 1
    },
    {
      "element": "H",
      "position": [
        2.839961608297174,
        -1.8557260115195717,
        -1.1314088023553412
      ],
      "atomic_number": 1
    },
    {
      "element": "H",
      "position": [
        0.34774298761291145,
        1.3000089111996251,
        1.0434854189331784
      ],
      "atomic_number": 1
    },
    {
      "element": "H",
      "position": [
        0.4098502664947122,
        2.088506094850785,
        -0.5548573071029549
      ],
      "atomic_number": 1
    },
    {
      "element": "H",
      "position": [
        -1.879479980616513,
        1.8335500440595778,
        -0.0440828412201677
      ],
      "atomic_number": 1
    },
    {
      "element": "H",
      "position": [
        -1.530034156803624,
        0.6235870211025495,
        -1.2774413246573382
      ],
      "atomic_number": 1
    },
    {
      "element": "H",
      "position": [
        -1.711438538453752,
        0.14884214020213427,
        1.7512819412898661
      ],
      "atomic_number": 1
    },
    {
      "element": "H",
      "position": [
        -1.2616036070206083,
        -1.099613407249388,
        0.6232236345439914
      ],
      "atomic_number": 1
    },
    {
      "element": "H",
      "position": [
        -4.052108303490692,
        1.3211538826270426,
        -0.016384593658058715
      ],
      "atomic_number": 1
    },
    {
      "element": "H",
      "position": [
        -4.289715721256529,
        0.9339186509820553,
        1.7062137244276796
      ],
      "atomic_number": 1
    },
    {
      "element": "H",
      "position": [
        -6.018039733331985,
        -0.6162606895856292,
        1.2148366682159293
      ],
      "atomic_number": 1
    },
    {
      "element": "H",
      "position": [
        -6.2568718159064165,
        0.4997044849603173,
        -0.13940929337724262
      ],
      "atomic_number": 1
    },
    {
      "element": "H",
      "position": [
        -5.503188470054199,
        -2.268230190354421,
        -0.2576287585962131
      ],
      "atomic_number": 1
    },
    {
      "element": "H",
      "position": [
        -5.535280887548218,
        -1.1497393884160925,
        -1.6306471410601384
      ],
      "atomic_number": 1
    },
    {
      "element": "H",
      "position": [
        -3.1878516789042894,
        -2.29326645084597,
        -0.6580404292404947
      ],
      "atomic_number": 1
    },
    {
      "element": "H",
      "position": [
        -3.2605904913260284,
        -0.7494599419120855,
        -1.5361024763985012
      ],
      "atomic_number": 1
    },
    {
      "element": "H",
      "position": [
        2.5368381492160763,
        2.0692851657265012,
        0.6577248432537057
      ],
      "atomic_number": 1
    },
    {
      "element": "H",
      "position": [
        4.932623243578896,
        2.0362277826141226,
        1.1277045649940765
      ],
      "atomic_number": 1
    }
  ]
}