{
  "atoms": [
    {
      "element": "O",
      "position": [
        3.2699231603781804,
        0.46746944200361046,
        0.20819891067806623
      ],
      "atomic_number": 8
    },
    {
      "element": "C",
      "position": [
        2.4205243122194906,
        -0.6267081747378787,
        -0.11705720991168445
      ],
      "atomic_number": 6
    },
    {
      "element": "C",
      "position": [
        0.9451674169750846,
        -0.3388333567544339,
        0.20311595291467843
      ],
      "atomic_number": 6
    },
    {
      "element": "O",
      "position": [
        0.2009936472691472,
        -1.5382139048818684,
        -0.05073524622949909
      ],
      "atomic_number": 8
    },
    {
      "element": "C",
      "position": [
        -1.1900115995186042,
        -1.364707643108508,
        -0.2961176955498919
      ],
      "atomic_number": 6
    },
    {
      "element": "O",
      "position": [
        -1.8494143621994463,
        -2.470692315630986,
        0.31066769155993323
      ],
      "atomic_number": 8
    },
    {
      "element": "C",
      "position": [
        -1.7916024289437888,
        -0.07866733918486506,
        0.2994500072038741
      ],
      "atomic_number": 6
    },
    {
      "element": "O",
      "position": [
        -1.681688870629362,
        -0.13253887931393127,
        1.737209256647798
      ],
      "atomic_number": 8
    },
    {
      "element": "C",
      "position": [
        -1.0518713154840298,
        1.1601183997962614,
        -0.20663593687104084
      ],
      "atomic_number": 6
    },
    {
      "element": "O",
      "position": [
        -1.7263949232355666,
        1.7089742445409737,
        -1.348044665715009
      ],
      "atomic_number": 8
    },
    {
      "element": "C",
      "position": [
        0.40055879225208557,
        0.8467090148295663,
        -0.6085975723978476
      ],
      "atomic_number": 6
    },
    {
      "element": "O",
      "position": [
        1.197134891648268,
        2.0317023375829972,
        -0.4738161982601993
      ],
      "atomic_number": 8
    },
    {
      "element": "H",
      "position": [
        2.9769613591750415,
        1.2228868887657574,
        -0.341139256215496
      ],
      "atomic_number": 1
    },
    {
      "element": "H",
      "position": [
        2.761545255091743,
        -1.5002695254874459,
        0.4491979908801332
      ],
      "atomic_number": 1
    },
    {
      "element": "H",
      "position": [
        2.550171366714729,
        -0.8721883454509993,
        -1.1772927581736263
      ],
      "atomic_number": 1
    },
    {
      "element": "H",
      "position": [
        0.8869872496667462,
        -0.10194288546974643,
        1.2731608249220212
      ],
      "atomic_number": 1
    },
    {
      "element": "H",
      "position": [
        -1.363385502906666,
        -1.4020223609634768,
        -1.3775057296448092
      ],
      "atomic_number": 1
    },
    {
      "element": "H",
      "position": [
        -1.4908763570050856,
        -3.249409272298241,
        -0.14895469780313234
      ],
      "atomic_number": 1
    },
    {
      "element": "H",
      "position": [
        -2.8625285638352893,
        -0.026479617535447243,
        0.07314807545918375
      ],
      "atomic_number": 1
    },
    {
      "element": "H",
      "position": [
        -1.9175838696086878,
        -1.0562867860692446,
        1.9667945502406876
      ],
      "atomic_number": 1
    },
    {
      "element": "H",
      "position": [
        -1.0722943899760615,
        1.9406638309095456,
        0.5638869402825671
      ],
      "atomic_number": 1
    },
    {
      "element": "H",
      "position": [
        -1.2247893065983722,
        2.505444531488076,
        -1.6082454704534694
      ],
      "atomic_number": 1
    },
    {
      "element": "H",
      "position": [
        0.4260453561043088,
        0.587448863865544,
        -1.674954038278857
      ],
      "atomic_number": 1
    },
    {
      "element": "H",
      "position": [
        1.1864286824455916,
        2.2875428531049273,
        0.4699595327311494
      ],
      "atomic_number": 1
    }
  ]
}